odoo8_addon_hr_expense_analytic_default-8.0.0.1.0.99.dev14-nspkg.pth
odoo_addons/hr_expense_analytic_default/__init__.py
odoo_addons/hr_expense_analytic_default/__openerp__.py
odoo_addons/hr_expense_analytic_default/expense_analytic_default.py
odoo_addons/hr_expense_analytic_default/expense_analytic_default_demo.xml
odoo_addons/hr_expense_analytic_default/hr_employee_view.xml
odoo_addons/hr_expense_analytic_default/hr_expense_view.xml
odoo_addons/hr_expense_analytic_default/i18n/ar.po
odoo_addons/hr_expense_analytic_default/i18n/de.po
odoo_addons/hr_expense_analytic_default/i18n/es.po
odoo_addons/hr_expense_analytic_default/i18n/fi.po
odoo_addons/hr_expense_analytic_default/i18n/fr.po
odoo_addons/hr_expense_analytic_default/i18n/hr_expense_analytic_default.pot
odoo_addons/hr_expense_analytic_default/i18n/it.po
odoo_addons/hr_expense_analytic_default/i18n/nl.po
odoo_addons/hr_expense_analytic_default/i18n/nl_NL.po
odoo_addons/hr_expense_analytic_default/i18n/pt_BR.po
odoo_addons/hr_expense_analytic_default/i18n/ro.po
odoo_addons/hr_expense_analytic_default/i18n/sl.po
odoo_addons/hr_expense_analytic_default/static/description/icon.png
odoo8_addon_hr_expense_analytic_default-8.0.0.1.0.99.dev14.dist-info/METADATA
odoo8_addon_hr_expense_analytic_default-8.0.0.1.0.99.dev14.dist-info/WHEEL
odoo8_addon_hr_expense_analytic_default-8.0.0.1.0.99.dev14.dist-info/namespace_packages.txt
odoo8_addon_hr_expense_analytic_default-8.0.0.1.0.99.dev14.dist-info/top_level.txt
odoo8_addon_hr_expense_analytic_default-8.0.0.1.0.99.dev14.dist-info/RECORD
