Metadata-Version: 2.1
Name: odoo8-addon-hr-expense-analytic-default
Version: 8.0.0.1.0.99.dev14
Summary: Manage default analytic account on expenses
Home-page: http://www.akretion.com
Author: Akretion
License: AGPL-3
Platform: UNKNOWN
Classifier: Programming Language :: Python
Classifier: Framework :: Odoo
Classifier: License :: OSI Approved :: GNU Affero General Public License v3
Requires-Python: ~=2.7
Requires-Dist: odoo (<9.0a,>=8.0a)
